{
    "workflow": {
        "root": null,
        "Templates": [],
        "nodeList": [
            "SnappyHexMesh",
            "GeometryDefiner",
            "BlockMesh",
            "BoundaryCondition"
        ],
        "nodes": {
            "SnappyHexMesh": {
                "Template": "openFOAM.mesh.SnappyHexMesh.jsonForm"
            },
            "GeometryDefiner": {
                "Template": "openFOAM.mesh.GeometryDefiner.jsonForm"
            },
            "BlockMesh": {
                "Template": "openFOAM.mesh.BlockMesh.jsonForm"
            },
            "BoundaryCondition": {
                "Template": "BC.jsonForm"
            }
        }
    }
}
