{
    "workflow": {
        "root": null,
        "Templates": [],
        "nodeList": [
            "CopyDirectory",
            "RunPythonScript",
            "RunOsCommand",
            "BlockMesh",
            "GeometryDefiner",
            "SnappyHexMesh",
            "ControlDict",
            "FvSchemes",
            "FvSolution",
            "TransportProperties",
            "RASProperties"
        ],
        "nodes": {
            "CopyDirectory": {
                "Template": "general.CopyDirectory"
            },
            "RunPythonScript": {
                "Template": "general.RunPythonScript"
            },
            "RunOsCommand":{
                "Template": "general.RunOsCommand"
            },
            "BlockMesh":{
                "Template": "GeometryDefiner.BlockMeshTemplate"
            },
            "GeometryDefiner":{
                "Template": "GeometryDefiner.GeometryDefinerTemplate"
            },
            "SnappyHexMesh":{
                "Execution": {
                    "type": "snappyHexMesh",
                    "input_parameters": {
                        "formData": "{WebGui.formData}"
                    }
                },
                "GUI": {
                    "Type": "WebGuiNode",
                    "Properties": {
                    },
                    "WebGui": {
                        "Template": "openFOAM.simpleFOAM.WebGui.SnappyMesh"
                    }
                }
            },
            "ControlDict":{
                "Execution": {
                    "type": "controlDict",
                    "input_parameters": {
                        "formData": "{WebGui.formData}"
                    }
                },
                "GUI": {
                    "Type": "WebGuiNode",
                    "Properties": {
                    },
                    "WebGui": {
                        "Template": "openFOAM.simpleFOAM.WebGui.ControlDict"
                    }
                }
            },
            "FvSchemes":{
                "Execution": {
                    "type": "fvSchemes",
                    "input_parameters": {
                        "formData": "{WebGui.formData}"
                    }
                },
                "GUI": {
                    "Type": "WebGuiNode",
                    "Properties": {
                    },
                    "WebGui": {
                        "Template": "openFOAM.simpleFOAM.WebGui.FvSchemes"
                    }
                }
            },
            "FvSolution":{
                "Execution": {
                    "type": "fvSolution",
                    "input_parameters": {
                        "formData": "{WebGui.formData}"
                    }
                },
                "GUI": {
                    "Type": "WebGuiNode",
                    "Properties": {
                    },
                    "WebGui": {
                        "Template": "openFOAM.simpleFOAM.WebGui.FvSolution"
                    }
                }
            },
            "TransportProperties":{
                "Execution": {
                    "type": "transportProperties",
                    "input_parameters": {
                        "formData": "{WebGui.simpleFOAM.WebGui.formData}"
                    }
                },
                "GUI": {
                    "Type": "WebGuiNode",
                    "Properties": {
                    },
                    "WebGui": {
                        "Template": "openFOAM.simpleFOAM.WebGui.TransportProperties"
                    }
                }
            },
            "RASProperties":{
                "Execution": {
                    "type": "RASProperties",
                    "input_parameters": {
                        "formData": "{WebGui.formData}"
                    }
                },
                "GUI": {
                    "Type": "WebGuiNode",
                    "Properties": {
                    },
                    "WebGui": {
                        "Template": "openFOAM.simpleFOAM.WebGui.RASProperties"
                    }
                }
            }
        }
    }
}
